nonebot_plugin_mccheck/__init__.py
nonebot_plugin_mccheck/configs.py
nonebot_plugin_mccheck/language.json
nonebot_plugin_mccheck/templates/Minecraft_AE.ttf
nonebot_plugin_mccheck/templates/README.md
nonebot_plugin_mccheck/templates/background.png
nonebot_plugin_mccheck/templates/default.html
nonebot_plugin_mccheck/templates/imagelesshoverbg.png
nonebot_plugin_mccheck/templates/main.css
nonebot_plugin_mccheck/templates/no_favicon.png
nonebot_plugin_mccheck/utils.py
nonebot_plugin_mccheck-0.3.1.dist-info/METADATA
nonebot_plugin_mccheck-0.3.1.dist-info/WHEEL
nonebot_plugin_mccheck-0.3.1.dist-info/licenses/LICENSE
nonebot_plugin_mccheck-0.3.1.dist-info/RECORD
