Metadata-Version: 2.4
Name: nonebot-plugin-mccheck
Version: 0.3.1
Summary: Minecraft服务器状态查询的nonebot插件，支持IPv6/Minecraft server status query plugin for nonebot, IPv6 supported
License: GPL-3.0
License-File: LICENSE
Keywords: nonebot,nonebot2,minecraft,i18n,plugin,server
Author: molanp
Author-email: molanpp@outlook.com
Classifier: License :: OSI Approved :: GNU General Public License v3 (GPLv3)
Classifier: Programming Language :: Python :: 2
Classifier: Programming Language :: Python :: 2.7
Classifier: Programming Language :: Python :: 3
Classifier: Programming Language :: Python :: 3.4
Classifier: Programming Language :: Python :: 3.5
Classifier: Programming Language :: Python :: 3.6
Classifier: Programming Language :: Python :: 3.7
Classifier: Programming Language :: Python :: 3.8
Classifier: Programming Language :: Python :: 3.9
Classifier: Programming Language :: Python :: 3.10
Classifier: Programming Language :: Python :: 3.11
Classifier: Programming Language :: Python :: 3.12
Classifier: Programming Language :: Python :: 3.13
Classifier: Programming Language :: Python :: 3.14
Requires-Dist: dnspython (>=2.5.0)
Requires-Dist: mcstatus (>=12.0.0)
Requires-Dist: nonebot-plugin-alconna (>=0.48.0)
Requires-Dist: nonebot-plugin-htmlrender (>=0.3.5)
Requires-Dist: nonebot-plugin-uninfo (>=0.7.0)
Requires-Dist: nonebot2 (>=2.2.0)
Project-URL: Homepage, https://github.com/molanp/nonebot_plugin_mccheck
Project-URL: Repository, https://github.com/molanp/nonebot_plugin_mccheck
